pythia/__init__.py
pythia/ai_hallucination.py
pythia/llm_extractor.py
pythia/prompt_gpt.py
pythia/template.py
pythia/validator.py
pythia/validator_call.py
pythia/config/config.yaml
pythia/evaluators/__init__.py
pythia/evaluators/_evaluators.py
pythia/evaluators/checkers.py
pythia/evaluators/extractors.py
pythia/evaluators/models.py
pythia/evaluators/utils.py
pythia/evaluators/prompts/__init__.py
pythia/evaluators/prompts/grading.py
pythia/evaluators/prompts/lynx_qa.py
pythia/evaluators/prompts/pythiav1.py
pythia/evaluators/strategies/__init__.py
pythia/evaluators/strategies/grading.py
pythia/evaluators/strategies/lynxqa.py
pythia/evaluators/strategies/pythiav1.py
pythia/validators/__init__.py
pythia/validators/detect_gibberish.py
pythia/validators/detect_pii.py
pythia/validators/detect_prompt_injection.py
pythia/validators/detect_secrets.py
pythia/validators/detect_toxicity.py
pythia/validators/extracted_summary_sentences_match.py
pythia/validators/mention_drugs.py
pythia/validators/provenance_embeddings.py
pythia/validators/provenance_llm.py
pythia/validators/qa_relevance.py
pythia/validators/saliency_check.py
pythia/validators/secrets_present.py
pythia/validators/wiki_provenance.py
askpythia-1.3.3.dist-info/LICENSE
askpythia-1.3.3.dist-info/METADATA
askpythia-1.3.3.dist-info/WHEEL
askpythia-1.3.3.dist-info/top_level.txt
askpythia-1.3.3.dist-info/RECORD
