Metadata-Version: 2.1
Name: askpythia
Version: 1.3.3
Summary: AI Hallucination tool including basic validators
Home-page: https://wisecube.atlassian.net/wiki/spaces/OR/pages/147128324/AI+Hallucination+API+Pythia
Author: Wisecube.ai
Author-email: info@wisecube.ai
License: UNKNOWN
Platform: UNKNOWN
Classifier: Programming Language :: Python :: 3
Classifier: License :: OSI Approved :: MIT License
Classifier: Operating System :: OS Independent
Requires-Python: >=3.10
License-File: LICENSE
Requires-Dist: boto3 (~=1.35.44)
Requires-Dist: litellm (==1.52.6)
Requires-Dist: openai (>=1.54.0)
Requires-Dist: tqdm (~=4.66.5)
Requires-Dist: pydantic (~=2.9.2)
Requires-Dist: typing-extensions (==4.12.2)
Requires-Dist: numpy (==1.23.2)
Requires-Dist: llm-guard (==0.3.14)
